slixmpp_omemo/__init__.py
slixmpp_omemo/base_session_manager.py
slixmpp_omemo/py.typed
slixmpp_omemo/version.py
slixmpp_omemo/xep_0384.py
slixmpp_omemo-2.1.0.dist-info/licenses/LICENSE
slixmpp_omemo-2.1.0.dist-info/METADATA
slixmpp_omemo-2.1.0.dist-info/WHEEL
slixmpp_omemo-2.1.0.dist-info/top_level.txt
slixmpp_omemo-2.1.0.dist-info/RECORD
