Metadata-Version: 2.4
Name: slixmpp-omemo
Version: 2.1.0
Summary: OMEMO plugin for Slixmpp
Author-email: "Tim Henkes (Syndace)" <me@syndace.dev>
Maintainer-email: "Tim Henkes (Syndace)" <me@syndace.dev>
License-Expression: AGPL-3.0-only
Project-URL: Documentation, https://slixmpp-omemo.readthedocs.io/
Project-URL: Repository, https://github.com/Syndace/slixmpp-omemo
Project-URL: Issues, https://github.com/Syndace/slixmpp-omemo/issues
Project-URL: Changelog, https://github.com/Syndace/slixmpp-omemo/blob/main/CHANGELOG.md
Classifier: Development Status :: 4 - Beta
Classifier: Programming Language :: Python :: 3
Classifier: Programming Language :: Python :: 3 :: Only
Classifier: Programming Language :: Python :: 3.10
Classifier: Programming Language :: Python :: 3.11
Classifier: Programming Language :: Python :: 3.12
Classifier: Programming Language :: Python :: 3.13
Classifier: Programming Language :: Python :: 3.14
Classifier: Programming Language :: Python :: Implementation :: CPython
Classifier: Programming Language :: Python :: Implementation :: PyPy
Classifier: Intended Audience :: Developers
Classifier: Topic :: Communications :: Chat
Classifier: Topic :: Internet :: XMPP
Classifier: Topic :: Security :: Cryptography
Classifier: Topic :: Software Development :: Libraries :: Python Modules
Requires-Python: >=3.10
License-File: LICENSE
Requires-Dist: slixmpp<2,>=1.8.0
Requires-Dist: OMEMO<3,>=2.0.0
Requires-Dist: Oldmemo[xml]<3,>=2.0.0
Requires-Dist: Twomemo[xml]<3,>=2.0.0
Requires-Dist: typing-extensions>=4.4.0
Provides-Extra: docs
Requires-Dist: sphinx; extra == "docs"
Requires-Dist: sphinx-rtd-theme; extra == "docs"
Requires-Dist: sphinx-autodoc-typehints; extra == "docs"
Provides-Extra: test
Requires-Dist: pytest; extra == "test"
Requires-Dist: pytest-asyncio; extra == "test"
Requires-Dist: pytest-cov; extra == "test"
Provides-Extra: lint
Requires-Dist: mypy; extra == "lint"
Requires-Dist: pylint; extra == "lint"
Requires-Dist: flake8; extra == "lint"
Requires-Dist: flake8-pyproject; extra == "lint"
Provides-Extra: dev
Requires-Dist: slixmpp-omemo[docs,lint,test]; extra == "dev"
Dynamic: license-file
